LICENSE.txt
README.md
setup.py
novigi_common.egg-info/PKG-INFO
novigi_common.egg-info/SOURCES.txt
novigi_common.egg-info/dependency_links.txt
novigi_common.egg-info/requires.txt
novigi_common.egg-info/top_level.txt
novigi_common/custom_plugings/custom_plugin.py
novigi_common/hooks/datalake_s3_hook.py
novigi_common/hooks/odbc_hook.py
novigi_common/hooks/postgres_hook.py
novigi_common/hooks/sample_custom_hook.py
novigi_common/operators/custom_csv_to_s3_opertor.py
novigi_common/operators/custom_file_load_operator.py
novigi_common/operators/mssql_to_s3_generic_operator.py
novigi_common/operators/mssql_to_s3_operator.py
novigi_common/operators/novigi_csv_to_db.py
novigi_common/operators/novigi_excel_to_csv.py
novigi_common/operators/novigi_json_to_csv_operator.py
novigi_common/operators/novigi_xls_to_csv_operator.py
novigi_common/operators/s3_to_redshift_staging_copy_operator.py
novigi_common/utils/custom_error_emails.py