Metadata-Version: 2.1
Name: novigi-common
Version: 1.0.7
Summary: Novigi Custom Airflow operators, hooks and plugins
Author: Novigi
Author-email: integration@novigi.com.au
License: MIT
Platform: UNKNOWN
License-File: LICENSE.txt
